quickdrop/__init__.py
quickdrop/quickdrop.py
quickdrop-0.1.dist-info/METADATA
quickdrop-0.1.dist-info/WHEEL
quickdrop-0.1.dist-info/entry_points.txt
quickdrop-0.1.dist-info/top_level.txt
quickdrop-0.1.dist-info/RECORD
