Metadata-Version: 2.1
Name: quickdrop
Version: 0.1
Summary: Quickly get a shared link for any file or folder in a Dropbox-synced folder
Home-page: https://github.com/zevaverbach/quickdrop
License: UNKNOWN
Platform: UNKNOWN
Requires-Dist: dropbox
Requires-Dist: Click
Requires-Dist: pyperclip
